{
	"order": 11,
	"impact": 2,
	"unchoosable": true,
	"name": "Zombie Husk",
	"description": "A sentient colony of mushrooms inhabiting the corpse of a husk. Can only heal via rotten flesh",
	"powers": [
		"jorigins:base/vessel",
		"jorigins:base/vesselhealth",
		"jorigins:hostswap",
		"jorigins:husk",
		"jorigins:spawn/desert",
		"jorigins:behaviour/outcast",
		"jorigins:behaviour/passivezombie",
		"jorigins:mushroomscraps",
		"jorigins:cave/miningbuffs",
		"jorigins:testpowers",
		"jorigins:water/nonaquatic"
		],
	"icon": {
		"id": "minecraft:brown_mushroom"
	}
}